[{"date":"Wed, 08 Jan 2014 15:42:25 GMT","sloc":32,"lloc":17,"functions":2,"deliveredBugs":0.1696829896013426,"maintainability":65.77283527534173,"lintErrors":0,"difficulty":9.642857142857142},{"date":"Wed, 08 Jan 2014 15:43:33 GMT","sloc":32,"lloc":17,"functions":2,"deliveredBugs":0.1696829896013426,"maintainability":65.77283527534173,"lintErrors":0,"difficulty":9.642857142857142},{"date":"Wed, 08 Jan 2014 15:46:36 GMT","sloc":32,"lloc":17,"functions":2,"deliveredBugs":0.1696829896013426,"maintainability":65.77283527534173,"lintErrors":0,"difficulty":9.642857142857142}]